apify/Actor.py
apify/ApifyABC.py
apify/Crawler.py
apify/Dataset.py
apify/Queue.py
apify/Store.py
apify/__init__.py
apify/common.py
apify/functions.py
apifyunofficial/Actor.py
apifyunofficial/ApifyABC.py
apifyunofficial/Crawler.py
apifyunofficial/Dataset.py
apifyunofficial/Queue.py
apifyunofficial/Store.py
apifyunofficial/__init__.py
apifyunofficial/common.py
apifyunofficial/functions.py
apifyunofficial-0.0.3.dist-info/LICENSE
apifyunofficial-0.0.3.dist-info/METADATA
apifyunofficial-0.0.3.dist-info/WHEEL
apifyunofficial-0.0.3.dist-info/top_level.txt
apifyunofficial-0.0.3.dist-info/RECORD
