Metadata-Version: 2.1
Name: apifyunofficial
Version: 0.0.3
Summary: Unofficial client for the apify.com API
Home-page: https://github.com/ctrl-q/apify
Author: ctrl-q
Author-email: 
License: GPLv3
Platform: UNKNOWN
Classifier: License :: OSI Approved :: GNU General Public License v3 (GPLv3)
Classifier: Programming Language :: Python
Classifier: Programming Language :: Python :: 3
Classifier: Programming Language :: Python :: 3.6
Classifier: Programming Language :: Python :: Implementation :: CPython
Classifier: Programming Language :: Python :: Implementation :: PyPy
Requires-Python: >=3.0.0
Requires-Dist: requests
